{
  "updatedAt": "2026-05-09T14:20:00Z",
  "marketIndex": 1000.0,
  "rawAveragePrice": 1.86,
  "topGainers": [
    {
      "ticker": "FRBY",
      "chg24h": 3.45
    },
    {
      "ticker": "GVON",
      "chg24h": 1.74
    },
    {
      "ticker": "SLNA",
      "chg24h": 1.13
    },
    {
      "ticker": "GAGA",
      "chg24h": 0.95
    },
    {
      "ticker": "JBBR",
      "chg24h": 0.7
    }
  ],
  "topLosers": [
    {
      "ticker": "ICE",
      "chg24h": -1.67
    },
    {
      "ticker": "LUZI",
      "chg24h": -1.41
    },
    {
      "ticker": "BFRY",
      "chg24h": -1.1
    },
    {
      "ticker": "TATE",
      "chg24h": -1.08
    },
    {
      "ticker": "BLPK",
      "chg24h": -1.03
    }
  ],
  "sectorIndices": [
    {
      "sector": "Afropop",
      "avgPrice": 0.79,
      "chg24h": 0.35,
      "members": [
        "TYLA",
        "REMA",
        "AYRA",
        "BRNA",
        "WZKD",
        "DAVD",
        "ASKE",
        "CKAY",
        "TEMS",
        "FRBY"
      ]
    },
    {
      "sector": "Alt",
      "avgPrice": 2.03,
      "chg24h": 0.09,
      "members": [
        "BILL",
        "LANA",
        "HZER",
        "ARCT",
        "LRDE",
        "TAME",
        "FTNS"
      ]
    },
    {
      "sector": "Electronic",
      "avgPrice": 2.23,
      "chg24h": 0.0,
      "members": [
        "GTTA",
        "CHRS",
        "FRED",
        "SKRL",
        "MRSH"
      ]
    },
    {
      "sector": "Hip-hop",
      "avgPrice": 1.79,
      "chg24h": -0.17,
      "members": [
        "DRKE",
        "TRVS",
        "KDOT",
        "ICE",
        "POST",
        "FUTR",
        "SVGE",
        "NCKI",
        "DCHI",
        "JCLE",
        "CRTI",
        "MTRO",
        "GNNA",
        "LBBY",
        "CNTC",
        "LTTO",
        "MGSN",
        "TYLR",
        "LUZI",
        "DONT"
      ]
    },
    {
      "sector": "Indie",
      "avgPrice": 0.68,
      "chg24h": 0.0,
      "members": [
        "MARI",
        "CLRO",
        "BEAB",
        "MTSK",
        "PHBE",
        "BOYG",
        "FAYE",
        "CGAS"
      ]
    },
    {
      "sector": "K-Pop",
      "avgPrice": 0.91,
      "chg24h": -0.41,
      "members": [
        "BTS",
        "BLPK",
        "NWJN",
        "STRY",
        "TWIC"
      ]
    },
    {
      "sector": "Latin",
      "avgPrice": 1.96,
      "chg24h": 0.03,
      "members": [
        "BNNY",
        "PESO",
        "ROSA",
        "KROL",
        "FEID",
        "RAUW",
        "MYKE",
        "OZNA",
        "JBLV",
        "MLMA",
        "ANUL",
        "SBYA",
        "QUVD",
        "FRZA",
        "JRRH"
      ]
    },
    {
      "sector": "Pop",
      "avgPrice": 2.82,
      "chg24h": 0.16,
      "members": [
        "SABR",
        "TSWF",
        "CHPL",
        "OLVR",
        "TATE",
        "DUAL",
        "ARGR",
        "SHRN",
        "HRST",
        "DOJA",
        "CHRL",
        "MLEY",
        "SHKR",
        "KTPR",
        "JBBR",
        "BRNO",
        "SLNA",
        "GAGA",
        "BENS",
        "GRAB",
        "CMLA",
        "SHMN",
        "TROY",
        "HLSY",
        "MADB"
      ]
    },
    {
      "sector": "R&B",
      "avgPrice": 1.62,
      "chg24h": 0.06,
      "members": [
        "WKND",
        "SZA",
        "BRYS",
        "SMRW",
        "BFRY",
        "PRTY",
        "GVON",
        "JHEN",
        "KHLN",
        "DCSR"
      ]
    }
  ],
  "artists": [
    {
      "ticker": "SABR",
      "name": "Sabrina Carpenter",
      "genre": "Pop",
      "spotifyId": "74KM79TiuVKeVCqs8QtB0B",
      "popularity": 92,
      "popularityDelta": 0,
      "followers": 32141621,
      "monthlyListeners": 68390941,
      "listenersSource": "calibrated-proxy",
      "image": "https://i.scdn.co/image/ab6761610000e5eb78e45cfa4697ce3c437cb455",
      "fairPrice": 3.04,
      "price": 3.04,
      "chg24h": 0.66,
      "volatility30d": 0.007,
      "volume": 3402,
      "youtube": {
        "subscribers": 13300000,
        "views": 6568392072,
        "videos": 199
      },
      "youtubeViews": 6568392072,
      "youtubeSubs": 13300000,
      "youtubeBoost": 0.2567,
      "chartPositions": {
        "hot100": 62
      },
      "chartBoost": 0.0975,
      "popularityBoost": 0.126
    },
    {
      "ticker": "TSWF",
      "name": "Taylor Swift",
      "genre": "Pop",
      "spotifyId": "06HL4z0CvFAxyc27GXpf02",
      "popularity": 98,
      "popularityDelta": 0,
      "followers": 156634307,
      "monthlyListeners": 101640002,
      "listenersSource": "calibrated-proxy",
      "image": "https://i.scdn.co/image/ab6761610000e5ebe2e8e7ff002a4afda1c7147e",
      "fairPrice": 5.04,
      "price": 5.04,
      "chg24h": 0.0,
      "volatility30d": 0.0,
      "volume": 7509,
      "youtube": {
        "subscribers": 63100000,
        "views": 44563826204,
        "videos": 658
      },
      "youtubeViews": 44563826204,
      "youtubeSubs": 63100000,
      "youtubeBoost": 0.3,
      "chartPositions": {
        "hot100": 17
      },
      "chartBoost": 0.21,
      "popularityBoost": 0.144
    },
    {
      "ticker": "CHPL",
      "name": "Chappell Roan",
      "genre": "Pop",
      "spotifyId": "7GlBOeep6PqTfFi59PTUUN",
      "popularity": 82,
      "popularityDelta": 0,
      "followers": 8158890,
      "monthlyListeners": 32658405,
      "listenersSource": "calibrated-proxy",
      "image": "https://i.scdn.co/image/ab6761610000e5ebd258ecb0d66244e6300bcf64",
      "fairPrice": 1.27,
      "price": 1.27,
      "chg24h": 0.0,
      "volatility30d": 0.0,
      "volume": 1714,
      "youtube": {
        "subscribers": 2400000,
        "views": 1420767405,
        "videos": 287
      },
      "youtubeViews": 1420767405,
      "youtubeSubs": 2400000,
      "youtubeBoost": 0.1971,
      "chartPositions": null,
      "chartBoost": 0.0,
      "popularityBoost": 0.096
    },
    {
      "ticker": "OLVR",
      "name": "Olivia Rodrigo",
      "genre": "Pop",
      "spotifyId": "1McMsnEElThX1knmY4oliG",
      "popularity": 90,
      "popularityDelta": 0,
      "followers": 53215966,
      "monthlyListeners": 60373513,
      "listenersSource": "calibrated-proxy",
      "image": "https://i.scdn.co/image/ab6761610000e5ebe654806251e2661def1f4e65",
      "fairPrice": 2.94,
      "price": 2.94,
      "chg24h": 0.68,
      "volatility30d": 0.012,
      "volume": 4377,
      "youtube": {
        "subscribers": 15900000,
        "views": 6691240051,
        "videos": 102
      },
      "youtubeViews": 6691240051,
      "youtubeSubs": 15900000,
      "youtubeBoost": 0.2602,
      "chartPositions": {
        "hot100": 4
      },
      "chartBoost": 0.2425,
      "popularityBoost": 0.12
    },
    {
      "ticker": "TATE",
      "name": "Tate McRae",
      "genre": "Pop",
      "spotifyId": "45dkTj5sMRSjrmBSBeiHym",
      "popularity": 88,
      "popularityDelta": 0,
      "followers": 10782558,
      "monthlyListeners": 45460343,
      "listenersSource": "calibrated-proxy",
      "image": "https://i.scdn.co/image/ab6761610000e5ebbed8016bd64422793ff3bc75",
      "fairPrice": 1.83,
      "price": 1.83,
      "chg24h": -1.08,
      "volatility30d": 0.007,
      "volume": 1970,
      "youtube": {
        "subscribers": 6650000,
        "views": 3225297521,
        "videos": 601
      },
      "youtubeViews": 3225297521,
      "youtubeSubs": 6650000,
      "youtubeBoost": 0.2308,
      "chartPositions": null,
      "chartBoost": 0.0,
      "popularityBoost": 0.114
    },
    {
      "ticker": "DUAL",
      "name": "Dua Lipa",
      "genre": "Pop",
      "spotifyId": "6M2wZ9GZgrQXHCFfjv46we",
      "popularity": 88,
      "popularityDelta": 0,
      "followers": 48008048,
      "monthlyListeners": 65382161,
      "listenersSource": "calibrated-proxy",
      "image": "https://i.scdn.co/image/ab6761610000e5eb0c68f6c95232e716f0abee8d",
      "fairPrice": 2.74,
      "price": 2.74,
      "chg24h": 0.0,
      "volatility30d": 0.005,
      "volume": 4157,
      "youtube": {
        "subscribers": 24800000,
        "views": 15905536978,
        "videos": 318
      },
      "youtubeViews": 15905536978,
      "youtubeSubs": 24800000,
      "youtubeBoost": 0.2848,
      "chartPositions": null,
      "chartBoost": 0.0,
      "popularityBoost": 0.114
    },
    {
      "ticker": "ARGR",
      "name": "Ariana Grande",
      "genre": "Pop",
      "spotifyId": "66CXWjxzNUsdJxJ2JdwvnR",
      "popularity": 92,
      "popularityDelta": 0,
      "followers": 111541655,
      "monthlyListeners": 84202795,
      "listenersSource": "calibrated-proxy",
      "image": "https://i.scdn.co/image/ab6761610000e5eb766397ec42a573a53eb5fb87",
      "fairPrice": 3.6,
      "price": 3.59,
      "chg24h": 0.0,
      "volatility30d": 0.0,
      "volume": 6337,
      "youtube": {
        "subscribers": 57100000,
        "views": 31826232317,
        "videos": 234
      },
      "youtubeViews": 31826232317,
      "youtubeSubs": 57100000,
      "youtubeBoost": 0.3,
      "chartPositions": null,
      "chartBoost": 0.0,
      "popularityBoost": 0.126
    },
    {
      "ticker": "SHRN",
      "name": "Ed Sheeran",
      "genre": "Pop",
      "spotifyId": "6eUKZXaKkcviH0Ku9w2n3V",
      "popularity": 89,
      "popularityDelta": 0,
      "followers": 126271839,
      "monthlyListeners": 83996027,
      "listenersSource": "calibrated-proxy",
      "image": "https://i.scdn.co/image/ab6761610000e5ebd55c95ad400aed87da52daec",
      "fairPrice": 3.57,
      "price": 3.56,
      "chg24h": 0.0,
      "volatility30d": 0.0,
      "volume": 6742,
      "youtube": {
        "subscribers": 59100000,
        "views": 37999180611,
        "videos": 756
      },
      "youtubeViews": 37999180611,
      "youtubeSubs": 59100000,
      "youtubeBoost": 0.3,
      "chartPositions": null,
      "chartBoost": 0.0,
      "popularityBoost": 0.117
    },
    {
      "ticker": "HRST",
      "name": "Harry Styles",
      "genre": "Pop",
      "spotifyId": "6KImCVD70vtIoJWnq6nGn3",
      "popularity": 90,
      "popularityDelta": 0,
      "followers": 35319999,
      "monthlyListeners": 66461642,
      "listenersSource": "calibrated-proxy",
      "image": "https://i.scdn.co/image/ab6761610000e5ebe309f8c3056a59f20d0968ca",
      "fairPrice": 3.02,
      "price": 3.02,
      "chg24h": 0.0,
      "volatility30d": 0.01,
      "volume": 3566,
      "youtube": {
        "subscribers": 15400000,
        "views": 8136230100,
        "videos": 21
      },
      "youtubeViews": 8136230100,
      "youtubeSubs": 15400000,
      "youtubeBoost": 0.2635,
      "chartPositions": {
        "hot100": 49
      },
      "chartBoost": 0.13,
      "popularityBoost": 0.12
    },
    {
      "ticker": "DOJA",
      "name": "Doja Cat",
      "genre": "Pop",
      "spotifyId": "5cj0lLjcoR7YOSnhnX0Po5",
      "popularity": 87,
      "popularityDelta": 0,
      "followers": 37074398,
      "monthlyListeners": 56716414,
      "listenersSource": "calibrated-proxy",
      "image": "https://i.scdn.co/image/ab6761610000e5eb8a0644455ebfa7d3976f5101",
      "fairPrice": 2.35,
      "price": 2.34,
      "chg24h": 0.0,
      "volatility30d": 0.0,
      "volume": 3653,
      "youtube": {
        "subscribers": 14000000,
        "views": 10962489061,
        "videos": 64
      },
      "youtubeViews": 10962489061,
      "youtubeSubs": 14000000,
      "youtubeBoost": 0.2676,
      "chartPositions": null,
      "chartBoost": 0.0,
      "popularityBoost": 0.111
    },
    {
      "ticker": "CHRL",
      "name": "Charli XCX",
      "genre": "Pop",
      "spotifyId": "25uiPmTg16RbhZWAqwLBy5",
      "popularity": 85,
      "popularityDelta": 0,
      "followers": 7009127,
      "monthlyListeners": 31499718,
      "listenersSource": "calibrated-proxy",
      "image": "https://i.scdn.co/image/ab6761610000e5eb6fa76436a2bba83b9f1d6fd1",
      "fairPrice": 1.25,
      "price": 1.25,
      "chg24h": 0.0,
      "volatility30d": 0.0,
      "volume": 1588,
      "youtube": {
        "subscribers": 4070000,
        "views": 2410898807,
        "videos": 329
      },
      "youtubeViews": 2410898807,
      "youtubeSubs": 4070000,
      "youtubeBoost": 0.2166,
      "chartPositions": null,
      "chartBoost": 0.0,
      "popularityBoost": 0.105
    },
    {
      "ticker": "MLEY",
      "name": "Miley Cyrus",
      "genre": "Pop",
      "spotifyId": "5YGY8feqx7naU7z4HrwZM6",
      "popularity": 84,
      "popularityDelta": 0,
      "followers": 27795099,
      "monthlyListeners": 60732291,
      "listenersSource": "calibrated-proxy",
      "image": "https://i.scdn.co/image/ab6761610000e5ebb14a2f1cede69cef4fb03b60",
      "fairPrice": 2.52,
      "price": 2.52,
      "chg24h": 0.0,
      "volatility30d": 0.0,
      "volume": 3163,
      "youtube": {
        "subscribers": 20000000,
        "views": 10910106266,
        "videos": 199
      },
      "youtubeViews": 10910106266,
      "youtubeSubs": 20000000,
      "youtubeBoost": 0.2737,
      "chartPositions": {
        "hot100": 97
      },
      "chartBoost": 0.01,
      "popularityBoost": 0.102
    },
    {
      "ticker": "SHKR",
      "name": "Shakira",
      "genre": "Pop",
      "spotifyId": "0EmeFodog0BfCgMzAIvKQp",
      "popularity": 89,
      "popularityDelta": 0,
      "followers": 42621076,
      "monthlyListeners": 83788773,
      "listenersSource": "calibrated-proxy",
      "image": "https://i.scdn.co/image/ab6761610000e5eb17f15f351cba70561ad8bcac",
      "fairPrice": 3.56,
      "price": 3.55,
      "chg24h": 0.28,
      "volatility30d": 0.006,
      "volume": 3917,
      "youtube": {
        "subscribers": 50200000,
        "views": 36080160427,
        "videos": 407
      },
      "youtubeViews": 36080160427,
      "youtubeSubs": 50200000,
      "youtubeBoost": 0.3,
      "chartPositions": null,
      "chartBoost": 0.0,
      "popularityBoost": 0.117
    },
    {
      "ticker": "KTPR",
      "name": "Katy Perry",
      "genre": "Pop",
      "spotifyId": "6jJ0s89eD6GaHleKKya26X",
      "popularity": 88,
      "popularityDelta": 0,
      "followers": 40359065,
      "monthlyListeners": 80532478,
      "listenersSource": "calibrated-proxy",
      "image": "https://i.scdn.co/image/ab6761610000e5eb4be5330bd48527f9dd620663",
      "fairPrice": 3.42,
      "price": 3.42,
      "chg24h": 0.59,
      "volatility30d": 0.016,
      "volume": 3812,
      "youtube": {
        "subscribers": 46900000,
        "views": 29868574721,
        "videos": 215
      },
      "youtubeViews": 29868574721,
      "youtubeSubs": 46900000,
      "youtubeBoost": 0.3,
      "chartPositions": null,
      "chartBoost": 0.0,
      "popularityBoost": 0.114
    },
    {
      "ticker": "JBBR",
      "name": "Justin Bieber",
      "genre": "Pop",
      "spotifyId": "1uNFoZAHBGtllmzznpCI3s",
      "popularity": 99,
      "popularityDelta": 0,
      "followers": 90279241,
      "monthlyListeners": 144031501,
      "listenersSource": "calibrated-proxy",
      "image": "https://i.scdn.co/image/ab6761610000e5ebaf20f7db5288bce9beede034",
      "fairPrice": 7.21,
      "price": 7.21,
      "chg24h": 0.7,
      "volatility30d": 0.035,
      "volume": 5701,
      "youtube": {
        "subscribers": 78200000,
        "views": 38263843289,
        "videos": 278
      },
      "youtubeViews": 38263843289,
      "youtubeSubs": 78200000,
      "youtubeBoost": 0.3,
      "chartPositions": {
        "hot100": 12
      },
      "chartBoost": 0.2225,
      "popularityBoost": 0.147
    },
    {
      "ticker": "BRNO",
      "name": "Bruno Mars",
      "genre": "Pop",
      "spotifyId": "0du5cEVh5yTK9QJze8zA0C",
      "popularity": 96,
      "popularityDelta": 0,
      "followers": 82450023,
      "monthlyListeners": 137559618,
      "listenersSource": "calibrated-proxy",
      "image": "https://i.scdn.co/image/ab6761610000e5ebc7688aad1bf03986934d7e26",
      "fairPrice": 6.96,
      "price": 6.96,
      "chg24h": 0.14,
      "volatility30d": 0.007,
      "volume": 5448,
      "youtube": {
        "subscribers": 43600000,
        "views": 25596255279,
        "videos": 121
      },
      "youtubeViews": 25596255279,
      "youtubeSubs": 43600000,
      "youtubeBoost": 0.3,
      "chartPositions": {
        "hot100": 2
      },
      "chartBoost": 0.2475,
      "popularityBoost": 0.138
    },
    {
      "ticker": "SLNA",
      "name": "Selena Gomez",
      "genre": "Pop",
      "spotifyId": "0C8ZW7ezQVs4URX5aX7Kqx",
      "popularity": 83,
      "popularityDelta": 0,
      "followers": 54253891,
      "monthlyListeners": 42898552,
      "listenersSource": "calibrated-proxy",
      "image": "https://i.scdn.co/image/ab6761610000e5eb815e520e3ce7fe210046ba66",
      "fairPrice": 1.79,
      "price": 1.79,
      "chg24h": 1.13,
      "volatility30d": 0.007,
      "volume": 4419,
      "youtube": {
        "subscribers": 35700000,
        "views": 16127111883,
        "videos": 212
      },
      "youtubeViews": 16127111883,
      "youtubeSubs": 35700000,
      "youtubeBoost": 0.2914,
      "chartPositions": null,
      "chartBoost": 0.0,
      "popularityBoost": 0.099
    },
    {
      "ticker": "GAGA",
      "name": "Lady Gaga",
      "genre": "Pop",
      "spotifyId": "1HY2Jd0NmPuamShAr6KMms",
      "popularity": 91,
      "popularityDelta": 0,
      "followers": 46288335,
      "monthlyListeners": 100140184,
      "listenersSource": "calibrated-proxy",
      "image": "https://i.scdn.co/image/ab6761610000e5ebaadc18cac8d48124357c38e6",
      "fairPrice": 4.27,
      "price": 4.26,
      "chg24h": 0.95,
      "volatility30d": 0.019,
      "volume": 4082,
      "youtube": {
        "subscribers": 30500000,
        "views": 24813379830,
        "videos": 260
      },
      "youtubeViews": 24813379830,
      "youtubeSubs": 30500000,
      "youtubeBoost": 0.2971,
      "chartPositions": null,
      "chartBoost": 0.0,
      "popularityBoost": 0.123
    },
    {
      "ticker": "BENS",
      "name": "Benson Boone",
      "genre": "Pop",
      "spotifyId": "22wbnEMDvgVIAGdFeek6ET",
      "popularity": 83,
      "popularityDelta": 0,
      "followers": 8074019,
      "monthlyListeners": 40330532,
      "listenersSource": "calibrated-proxy",
      "image": "https://i.scdn.co/image/ab6761610000e5ebb68234e1a673acc3d873d3e6",
      "fairPrice": 1.5,
      "price": 1.5,
      "chg24h": 0.0,
      "volatility30d": 0.0,
      "volume": 1705,
      "youtube": {
        "subscribers": 4480,
        "views": 1106357814,
        "videos": 101
      },
      "youtubeViews": 1106357814,
      "youtubeSubs": 4480,
      "youtubeBoost": 0.137,
      "chartPositions": null,
      "chartBoost": 0.0,
      "popularityBoost": 0.099
    },
    {
      "ticker": "GRAB",
      "name": "Gracie Abrams",
      "genre": "Pop",
      "spotifyId": "4tuJ0bMpJh08umKkEXKUI5",
      "popularity": 83,
      "popularityDelta": 0,
      "followers": 9403117,
      "monthlyListeners": 33373543,
      "listenersSource": "calibrated-proxy",
      "image": "https://i.scdn.co/image/ab6761610000e5ebf6d51e6f5342d2d363220920",
      "fairPrice": 1.29,
      "price": 1.29,
      "chg24h": 0.0,
      "volatility30d": 0.0,
      "volume": 1840,
      "youtube": {
        "subscribers": 1970000,
        "views": 980239340,
        "videos": 58
      },
      "youtubeViews": 980239340,
      "youtubeSubs": 1970000,
      "youtubeBoost": 0.1864,
      "chartPositions": null,
      "chartBoost": 0.0,
      "popularityBoost": 0.099
    },
    {
      "ticker": "CMLA",
      "name": "Camila Cabello",
      "genre": "Pop",
      "spotifyId": "4nDoRrQiYLoBzwC5BhVJzF",
      "popularity": 81,
      "popularityDelta": 0,
      "followers": 36412340,
      "monthlyListeners": 45093042,
      "listenersSource": "calibrated-proxy",
      "image": "https://i.scdn.co/image/ab6761610000e5eb76470faf6330235edbcb90a9",
      "fairPrice": 1.84,
      "price": 1.83,
      "chg24h": 0.0,
      "volatility30d": 0.0,
      "volume": 3621,
      "youtube": {
        "subscribers": 17100000,
        "views": 8030189854,
        "videos": 206
      },
      "youtubeViews": 8030189854,
      "youtubeSubs": 17100000,
      "youtubeBoost": 0.265,
      "chartPositions": null,
      "chartBoost": 0.0,
      "popularityBoost": 0.093
    },
    {
      "ticker": "SHMN",
      "name": "Shawn Mendes",
      "genre": "Pop",
      "spotifyId": "7n2wHs1TKAczGzO7Dd2rGr",
      "popularity": 84,
      "popularityDelta": 0,
      "followers": 46702015,
      "monthlyListeners": 48453341,
      "listenersSource": "calibrated-proxy",
      "image": "https://i.scdn.co/image/ab6761610000e5eb58b4b9419486550f6fda0535",
      "fairPrice": 2.02,
      "price": 2.01,
      "chg24h": 0.0,
      "volatility30d": 0.005,
      "volume": 4100,
      "youtube": {
        "subscribers": 30700000,
        "views": 15756218378,
        "videos": 195
      },
      "youtubeViews": 15756218378,
      "youtubeSubs": 30700000,
      "youtubeBoost": 0.2884,
      "chartPositions": null,
      "chartBoost": 0.0,
      "popularityBoost": 0.102
    },
    {
      "ticker": "TROY",
      "name": "Troye Sivan",
      "genre": "Pop",
      "spotifyId": "3WGpXCj9YhhfX11TToZcXP",
      "popularity": 75,
      "popularityDelta": 0,
      "followers": 9543543,
      "monthlyListeners": 18466756,
      "listenersSource": "calibrated-proxy",
      "image": "https://i.scdn.co/image/ab6761610000e5eb26e8cb3ff6fc7744b312811b",
      "fairPrice": 0.72,
      "price": 0.71,
      "chg24h": 0.0,
      "volatility30d": 0.0,
      "volume": 1854,
      "youtube": {
        "subscribers": 8220000,
        "views": 2252562216,
        "videos": 201
      },
      "youtubeViews": 2252562216,
      "youtubeSubs": 8220000,
      "youtubeBoost": 0.2275,
      "chartPositions": null,
      "chartBoost": 0.0,
      "popularityBoost": 0.075
    },
    {
      "ticker": "HLSY",
      "name": "Halsey",
      "genre": "Pop",
      "spotifyId": "26VFTg2z8YR0cCuwLzESi2",
      "popularity": 83,
      "popularityDelta": 0,
      "followers": 22989937,
      "monthlyListeners": 52366478,
      "listenersSource": "calibrated-proxy",
      "image": "https://i.scdn.co/image/ab6761610000e5eb15136101a0f63f0b2800b9dc",
      "fairPrice": 2.13,
      "price": 2.12,
      "chg24h": 0.0,
      "volatility30d": 0.0,
      "volume": 2877,
      "youtube": {
        "subscribers": 12500000,
        "views": 6470113909,
        "videos": 112
      },
      "youtubeViews": 6470113909,
      "youtubeSubs": 12500000,
      "youtubeBoost": 0.2554,
      "chartPositions": null,
      "chartBoost": 0.0,
      "popularityBoost": 0.099
    },
    {
      "ticker": "MADB",
      "name": "Madison Beer",
      "genre": "Pop",
      "spotifyId": "2kRfqPViCqYdSGhYSM9R0Q",
      "popularity": 76,
      "popularityDelta": 0,
      "followers": 9468770,
      "monthlyListeners": 17864728,
      "listenersSource": "calibrated-proxy",
      "image": "https://i.scdn.co/image/ab6761610000e5ebe49a051508f6c1eeaecff664",
      "fairPrice": 0.69,
      "price": 0.69,
      "chg24h": 0.0,
      "volatility30d": 0.005,
      "volume": 1846,
      "youtube": {
        "subscribers": 4060000,
        "views": 1258656659,
        "videos": 82
      },
      "youtubeViews": 1258656659,
      "youtubeSubs": 4060000,
      "youtubeBoost": 0.2038,
      "chartPositions": null,
      "chartBoost": 0.0,
      "popularityBoost": 0.078
    },
    {
      "ticker": "DRKE",
      "name": "Drake",
      "genre": "Hip-hop",
      "spotifyId": "3TVXtAsR1Inumwj472S9r4",
      "popularity": 98,
      "popularityDelta": 0,
      "followers": 110418298,
      "monthlyListeners": 89615491,
      "listenersSource": "calibrated-proxy",
      "image": "https://i.scdn.co/image/ab6761610000e5eb4293385d324db8558179afd9",
      "fairPrice": 3.87,
      "price": 3.87,
      "chg24h": 0.0,
      "volatility30d": 0.0,
      "volume": 6305,
      "youtube": {
        "subscribers": 32100000,
        "views": 22522059314,
        "videos": 103
      },
      "youtubeViews": 22522059314,
      "youtubeSubs": 32100000,
      "youtubeBoost": 0.2961,
      "chartPositions": null,
      "chartBoost": 0.0,
      "popularityBoost": 0.144
    },
    {
      "ticker": "TRVS",
      "name": "Travis Scott",
      "genre": "Hip-hop",
      "spotifyId": "0Y5tJX1MQlPlqiwlOH1tJY",
      "popularity": 92,
      "popularityDelta": 0,
      "followers": 43600979,
      "monthlyListeners": 63238860,
      "listenersSource": "calibrated-proxy",
      "image": "https://i.scdn.co/image/ab6761610000e5eb19c2790744c792d05570bb71",
      "fairPrice": 2.72,
      "price": 2.73,
      "chg24h": -0.36,
      "volatility30d": 0.007,
      "volume": 3962,
      "youtube": {
        "subscribers": 20700000,
        "views": 12001270993,
        "videos": 20
      },
      "youtubeViews": 12001270993,
      "youtubeSubs": 20700000,
      "youtubeBoost": 0.2762,
      "chartPositions": {
        "hot100": 88
      },
      "chartBoost": 0.0325,
      "popularityBoost": 0.126
    },
    {
      "ticker": "KDOT",
      "name": "Kendrick Lamar",
      "genre": "Hip-hop",
      "spotifyId": "2YZyLoL8N0Wb9xBt1NhZWg",
      "popularity": 91,
      "popularityDelta": 0,
      "followers": 47700865,
      "monthlyListeners": 71579918,
      "listenersSource": "calibrated-proxy",
      "image": "https://i.scdn.co/image/ab6761610000e5eb39ba6dcd4355c03de0b50918",
      "fairPrice": 3.0,
      "price": 3.0,
      "chg24h": 0.0,
      "volatility30d": 0.0,
      "volume": 4144,
      "youtube": {
        "subscribers": 20200000,
        "views": 12199373922,
        "videos": 40
      },
      "youtubeViews": 12199373922,
      "youtubeSubs": 20200000,
      "youtubeBoost": 0.2761,
      "chartPositions": null,
      "chartBoost": 0.0,
      "popularityBoost": 0.123
    },
    {
      "ticker": "ICE",
      "name": "Ice Spice",
      "genre": "Hip-hop",
      "spotifyId": "3LZZPxNDGDFVSIPqf4JuEf",
      "popularity": 73,
      "popularityDelta": 0,
      "followers": 5288770,
      "monthlyListeners": 15584947,
      "listenersSource": "calibrated-proxy",
      "image": "https://i.scdn.co/image/ab6761610000e5ebab47bb63dae13065213602cd",
      "fairPrice": 0.59,
      "price": 0.59,
      "chg24h": -1.67,
      "volatility30d": 0.004,
      "volume": 1380,
      "youtube": {
        "subscribers": 3790000,
        "views": 1270003593,
        "videos": 40
      },
      "youtubeViews": 1270003593,
      "youtubeSubs": 3790000,
      "youtubeBoost": 0.2028,
      "chartPositions": null,
      "chartBoost": 0.0,
      "popularityBoost": 0.069
    },
    {
      "ticker": "POST",
      "name": "Post Malone",
      "genre": "Hip-hop",
      "spotifyId": "246dkjvS1zLTtiykXe5h60",
      "popularity": 88,
      "popularityDelta": 0,
      "followers": 48667173,
      "monthlyListeners": 62045779,
      "listenersSource": "calibrated-proxy",
      "image": "https://i.scdn.co/image/ab6761610000e5ebe17c0aa1714a03d62b5ce4e0",
      "fairPrice": 2.79,
      "price": 2.79,
      "chg24h": 0.0,
      "volatility30d": 0.0,
      "volume": 4186,
      "youtube": {
        "subscribers": 28800000,
        "views": 20349960192,
        "videos": 184
      },
      "youtubeViews": 20349960192,
      "youtubeSubs": 28800000,
      "youtubeBoost": 0.2923,
      "chartPositions": {
        "hot100": 63
      },
      "chartBoost": 0.095,
      "popularityBoost": 0.114
    },
    {
      "ticker": "FUTR",
      "name": "Future",
      "genre": "Hip-hop",
      "spotifyId": "1RyvyyTE3xzB2ZywiAwp0i",
      "popularity": 91,
      "popularityDelta": 0,
      "followers": 24241105,
      "monthlyListeners": 54382495,
      "listenersSource": "calibrated-proxy",
      "image": "https://i.scdn.co/image/ab6761610000e5eb7565b356bc9d9394eefa2ccb",
      "fairPrice": 2.28,
      "price": 2.27,
      "chg24h": 0.0,
      "volatility30d": 0.0,
      "volume": 2954,
      "youtube": {
        "subscribers": 14900000,
        "views": 14473245240,
        "videos": 79
      },
      "youtubeViews": 14473245240,
      "youtubeSubs": 14900000,
      "youtubeBoost": 0.2742,
      "chartPositions": null,
      "chartBoost": 0.0,
      "popularityBoost": 0.123
    },
    {
      "ticker": "SVGE",
      "name": "21 Savage",
      "genre": "Hip-hop",
      "spotifyId": "1URnnhqYAYcrqrcwql10ft",
      "popularity": 86,
      "popularityDelta": 0,
      "followers": 25523005,
      "monthlyListeners": 39953712,
      "listenersSource": "calibrated-proxy",
      "image": "https://i.scdn.co/image/ab6761610000e5eb4f8f76117470957c0e81e5b2",
      "fairPrice": 1.63,
      "price": 1.62,
      "chg24h": 0.0,
      "volatility30d": 0.0,
      "volume": 3031,
      "youtube": {
        "subscribers": 10100000,
        "views": 6629762616,
        "videos": 166
      },
      "youtubeViews": 6629762616,
      "youtubeSubs": 10100000,
      "youtubeBoost": 0.2521,
      "chartPositions": null,
      "chartBoost": 0.0,
      "popularityBoost": 0.108
    },
    {
      "ticker": "NCKI",
      "name": "Nicki Minaj",
      "genre": "Hip-hop",
      "spotifyId": "0hCNtLu0JehylgoiP8L4Gh",
      "popularity": 89,
      "popularityDelta": 0,
      "followers": 34725546,
      "monthlyListeners": 48244201,
      "listenersSource": "calibrated-proxy",
      "image": "https://i.scdn.co/image/ab6761610000e5eb07a50f0a9a8f11e5a1102cbd",
      "fairPrice": 2.03,
      "price": 2.02,
      "chg24h": 0.5,
      "volatility30d": 0.007,
      "volume": 3536,
      "youtube": {
        "subscribers": 28100000,
        "views": 12624369816,
        "videos": 67
      },
      "youtubeViews": 12624369816,
      "youtubeSubs": 28100000,
      "youtubeBoost": 0.2825,
      "chartPositions": null,
      "chartBoost": 0.0,
      "popularityBoost": 0.117
    },
    {
      "ticker": "DCHI",
      "name": "Doechii",
      "genre": "Hip-hop",
      "spotifyId": "4E2rKHVDssGJm2SCDOMMJB",
      "popularity": 80,
      "popularityDelta": 0,
      "followers": 3562008,
      "monthlyListeners": 31725024,
      "listenersSource": "calibrated-proxy",
      "image": "https://i.scdn.co/image/ab6761610000e5ebca2fee52c41d3f58ceb6474b",
      "fairPrice": 1.23,
      "price": 1.23,
      "chg24h": 0.0,
      "volatility30d": 0.01,
      "volume": 1132,
      "youtube": {
        "subscribers": 3250000,
        "views": 1327690444,
        "videos": 302
      },
      "youtubeViews": 1327690444,
      "youtubeSubs": 3250000,
      "youtubeBoost": 0.201,
      "chartPositions": null,
      "chartBoost": 0.0,
      "popularityBoost": 0.09
    },
    {
      "ticker": "JCLE",
      "name": "J. Cole",
      "genre": "Hip-hop",
      "spotifyId": "6l3HvQ5sa6mXTsMTB19rO5",
      "popularity": 87,
      "popularityDelta": 0,
      "followers": 28300255,
      "monthlyListeners": 38230814,
      "listenersSource": "calibrated-proxy",
      "image": "https://i.scdn.co/image/ab6761610000e5ebc401ea77e86ee984b1ba9fc2",
      "fairPrice": 1.55,
      "price": 1.54,
      "chg24h": 0.0,
      "volatility30d": 0.0,
      "volume": 3192,
      "youtube": {
        "subscribers": 8440000,
        "views": 5305437125,
        "videos": 231
      },
      "youtubeViews": 5305437125,
      "youtubeSubs": 8440000,
      "youtubeBoost": 0.2447,
      "chartPositions": null,
      "chartBoost": 0.0,
      "popularityBoost": 0.111
    },
    {
      "ticker": "CRTI",
      "name": "Playboi Carti",
      "genre": "Hip-hop",
      "spotifyId": "699OTQXzgjhIYAHMy9RyPD",
      "popularity": 87,
      "popularityDelta": 0,
      "followers": 16211493,
      "monthlyListeners": 42114217,
      "listenersSource": "calibrated-proxy",
      "image": "https://i.scdn.co/image/ab6761610000e5ebba50ca67ffc3097f6ea1710a",
      "fairPrice": 1.68,
      "price": 1.69,
      "chg24h": 0.0,
      "volatility30d": 0.0,
      "volume": 2416,
      "youtube": {
        "subscribers": 4900000,
        "views": 2673313271,
        "videos": 70
      },
      "youtubeViews": 2673313271,
      "youtubeSubs": 4900000,
      "youtubeBoost": 0.2218,
      "chartPositions": null,
      "chartBoost": 0.0,
      "popularityBoost": 0.111
    },
    {
      "ticker": "MTRO",
      "name": "Metro Boomin",
      "genre": "Hip-hop",
      "spotifyId": "0iEtIxbK0KxaSlF7G42ZOp",
      "popularity": 86,
      "popularityDelta": 0,
      "followers": 12585649,
      "monthlyListeners": 42232404,
      "listenersSource": "calibrated-proxy",
      "image": "https://i.scdn.co/image/ab6761610000e5eb28f1e72b31e756ea3f3a51e7",
      "fairPrice": 1.68,
      "price": 1.67,
      "chg24h": 0.0,
      "volatility30d": 0.0,
      "volume": 2129,
      "youtube": {
        "subscribers": 3580000,
        "views": 3115489636,
        "videos": 145
      },
      "youtubeViews": 3115489636,
      "youtubeSubs": 3580000,
      "youtubeBoost": 0.2194,
      "chartPositions": null,
      "chartBoost": 0.0,
      "popularityBoost": 0.108
    },
    {
      "ticker": "GNNA",
      "name": "Gunna",
      "genre": "Hip-hop",
      "spotifyId": "2hlmm7s2ICUX0LVIhVFlZQ",
      "popularity": 87,
      "popularityDelta": 0,
      "followers": 11614993,
      "monthlyListeners": 35340939,
      "listenersSource": "calibrated-proxy",
      "image": "https://i.scdn.co/image/ab6761610000e5eba998bc86f87b9fe7e2466110",
      "fairPrice": 1.41,
      "price": 1.4,
      "chg24h": 0.0,
      "volatility30d": 0.0,
      "volume": 2045,
      "youtube": {
        "subscribers": 3610000,
        "views": 3384245160,
        "videos": 443
      },
      "youtubeViews": 3384245160,
      "youtubeSubs": 3610000,
      "youtubeBoost": 0.2211,
      "chartPositions": null,
      "chartBoost": 0.0,
      "popularityBoost": 0.111
    },
    {
      "ticker": "LBBY",
      "name": "Lil Baby",
      "genre": "Hip-hop",
      "spotifyId": "5f7VJjfbwm532GiveGC0ZK",
      "popularity": 88,
      "popularityDelta": 0,
      "followers": 23078979,
      "monthlyListeners": 32548284,
      "listenersSource": "calibrated-proxy",
      "image": "https://i.scdn.co/image/ab6761610000e5eb514da623c55dc9d2155705dd",
      "fairPrice": 1.34,
      "price": 1.35,
      "chg24h": 0.0,
      "volatility30d": 0.0,
      "volume": 2882,
      "youtube": {
        "subscribers": 10400000,
        "views": 11390614323,
        "videos": 139
      },
      "youtubeViews": 11390614323,
      "youtubeSubs": 10400000,
      "youtubeBoost": 0.2632,
      "chartPositions": null,
      "chartBoost": 0.0,
      "popularityBoost": 0.114
    },
    {
      "ticker": "CNTC",
      "name": "Central Cee",
      "genre": "Hip-hop",
      "spotifyId": "5H4yInM5zmHqpKIoMNAx4r",
      "popularity": 82,
      "popularityDelta": 0,
      "followers": 11038749,
      "monthlyListeners": 25459771,
      "listenersSource": "calibrated-proxy",
      "image": "https://i.scdn.co/image/ab6761610000e5eb6ce131983245fc2e6940f6c2",
      "fairPrice": 1.01,
      "price": 1.02,
      "chg24h": 0.0,
      "volatility30d": 0.0,
      "volume": 1993,
      "youtube": {
        "subscribers": 6820000,
        "views": 2490531356,
        "videos": 92
      },
      "youtubeViews": 2490531356,
      "youtubeSubs": 6820000,
      "youtubeBoost": 0.2262,
      "chartPositions": null,
      "chartBoost": 0.0,
      "popularityBoost": 0.096
    },
    {
      "ticker": "LTTO",
      "name": "Latto",
      "genre": "Hip-hop",
      "spotifyId": "3MdXrJWsbVzdn6fe5JYkSQ",
      "popularity": 79,
      "popularityDelta": 0,
      "followers": 2726366,
      "monthlyListeners": 16555040,
      "listenersSource": "calibrated-proxy",
      "image": "https://i.scdn.co/image/ab6761610000e5eb2d805d9a367bdad2096ab817",
      "fairPrice": 0.65,
      "price": 0.66,
      "chg24h": 0.0,
      "volatility30d": 0.0,
      "volume": 991,
      "youtube": {
        "subscribers": 2700000,
        "views": 1536643381,
        "videos": 534
      },
      "youtubeViews": 1536643381,
      "youtubeSubs": 2700000,
      "youtubeBoost": 0.2007,
      "chartPositions": {
        "hot100": 90
      },
      "chartBoost": 0.0275,
      "popularityBoost": 0.087
    },
    {
      "ticker": "MGSN",
      "name": "Megan Thee Stallion",
      "genre": "Hip-hop",
      "spotifyId": "181bsRPaVXVlUKXrxwZfHK",
      "popularity": 81,
      "popularityDelta": 0,
      "followers": 11575116,
      "monthlyListeners": 25877329,
      "listenersSource": "calibrated-proxy",
      "image": "https://i.scdn.co/image/ab6761610000e5eb65a9ac943abab7c9935ea282",
      "fairPrice": 1.03,
      "price": 1.02,
      "chg24h": 0.0,
      "volatility30d": 0.0,
      "volume": 2041,
      "youtube": {
        "subscribers": 7370000,
        "views": 3930652331,
        "videos": 378
      },
      "youtubeViews": 3930652331,
      "youtubeSubs": 7370000,
      "youtubeBoost": 0.2364,
      "chartPositions": null,
      "chartBoost": 0.0,
      "popularityBoost": 0.093
    },
    {
      "ticker": "TYLR",
      "name": "Tyler, The Creator",
      "genre": "Hip-hop",
      "spotifyId": "4V8LLVI7PbaPR0K2TGSxFF",
      "popularity": 87,
      "popularityDelta": 0,
      "followers": 26715888,
      "monthlyListeners": 41078349,
      "listenersSource": "calibrated-proxy",
      "image": "https://i.scdn.co/image/ab6761610000e5ebdf2728294ff77dd11eeb18fb",
      "fairPrice": 1.66,
      "price": 1.67,
      "chg24h": 0.0,
      "volatility30d": 0.0,
      "volume": 3101,
      "youtube": {
        "subscribers": 8190000,
        "views": 4059858433,
        "videos": 112
      },
      "youtubeViews": 4059858433,
      "youtubeSubs": 8190000,
      "youtubeBoost": 0.2389,
      "chartPositions": null,
      "chartBoost": 0.0,
      "popularityBoost": 0.111
    },
    {
      "ticker": "LUZI",
      "name": "Lil Uzi Vert",
      "genre": "Hip-hop",
      "spotifyId": "4O15NlyKLIASxsJ0PrXPfz",
      "popularity": 86,
      "popularityDelta": 0,
      "followers": 20349192,
      "monthlyListeners": 32585161,
      "listenersSource": "calibrated-proxy",
      "image": "https://i.scdn.co/image/ab6761610000e5eb62c272d76220f2e9dad56704",
      "fairPrice": 1.4,
      "price": 1.4,
      "chg24h": -1.41,
      "volatility30d": 0.007,
      "volume": 2707,
      "youtube": {
        "subscribers": 10300000,
        "views": 5983042479,
        "videos": 246
      },
      "youtubeViews": 5983042479,
      "youtubeSubs": 10300000,
      "youtubeBoost": 0.2505,
      "chartPositions": {
        "hot100": 70
      },
      "chartBoost": 0.0775,
      "popularityBoost": 0.108
    },
    {
      "ticker": "DONT",
      "name": "Don Toliver",
      "genre": "Hip-hop",
      "spotifyId": "4Gso3d4CscCijv0lmajZWs",
      "popularity": 91,
      "popularityDelta": 0,
      "followers": 8811313,
      "monthlyListeners": 48762687,
      "listenersSource": "calibrated-proxy",
      "image": "https://i.scdn.co/image/ab6761610000e5ebc52b798deb89eb8414a51b7b",
      "fairPrice": 2.19,
      "price": 2.2,
      "chg24h": -0.45,
      "volatility30d": 0.004,
      "volume": 1781,
      "youtube": {
        "subscribers": 2860000,
        "views": 2548389490,
        "videos": 250
      },
      "youtubeViews": 2548389490,
      "youtubeSubs": 2860000,
      "youtubeBoost": 0.2115,
      "chartPositions": {
        "hot100": 35
      },
      "chartBoost": 0.165,
      "popularityBoost": 0.123
    },
    {
      "ticker": "WKND",
      "name": "The Weeknd",
      "genre": "R&B",
      "spotifyId": "1Xyo4u8uXC1ZmMpatF05PJ",
      "popularity": 95,
      "popularityDelta": 0,
      "followers": 122116423,
      "monthlyListeners": 115876274,
      "listenersSource": "calibrated-proxy",
      "image": "https://i.scdn.co/image/ab6761610000e5ebc1719ac9e6a75c1c25835018",
      "fairPrice": 4.99,
      "price": 5.0,
      "chg24h": 0.0,
      "volatility30d": 0.0,
      "volume": 6630,
      "youtube": {
        "subscribers": 39600000,
        "views": 36353319792,
        "videos": 204
      },
      "youtubeViews": 36353319792,
      "youtubeSubs": 39600000,
      "youtubeBoost": 0.3,
      "chartPositions": null,
      "chartBoost": 0.0,
      "popularityBoost": 0.135
    },
    {
      "ticker": "SZA",
      "name": "SZA",
      "genre": "R&B",
      "spotifyId": "7tYKF4w9nC0nq9CsPZTHyP",
      "popularity": 89,
      "popularityDelta": 0,
      "followers": 35768294,
      "monthlyListeners": 69780365,
      "listenersSource": "calibrated-proxy",
      "image": "https://i.scdn.co/image/ab6761610000e5ebfd0a9fb6c252a3ba44079acf",
      "fairPrice": 2.84,
      "price": 2.83,
      "chg24h": 0.0,
      "volatility30d": 0.0,
      "volume": 3588,
      "youtube": {
        "subscribers": 6680000,
        "views": 5365757639,
        "videos": 38
      },
      "youtubeViews": 5365757639,
      "youtubeSubs": 6680000,
      "youtubeBoost": 0.2408,
      "chartPositions": null,
      "chartBoost": 0.0,
      "popularityBoost": 0.117
    },
    {
      "ticker": "BRYS",
      "name": "Bryson Tiller",
      "genre": "R&B",
      "spotifyId": "2EMAnMvWE2eb56ToJVfCWs",
      "popularity": 81,
      "popularityDelta": 0,
      "followers": 11023164,
      "monthlyListeners": 20324510,
      "listenersSource": "calibrated-proxy",
      "image": "https://i.scdn.co/image/ab6761610000e5ebb0ff28b9d4bed74c66901b2b",
      "fairPrice": 0.8,
      "price": 0.8,
      "chg24h": 0.0,
      "volatility30d": 0.0,
      "volume": 1992,
      "youtube": {
        "subscribers": 3650000,
        "views": 3356215322,
        "videos": 32
      },
      "youtubeViews": 3356215322,
      "youtubeSubs": 3650000,
      "youtubeBoost": 0.2212,
      "chartPositions": null,
      "chartBoost": 0.0,
      "popularityBoost": 0.093
    },
    {
      "ticker": "SMRW",
      "name": "Summer Walker",
      "genre": "R&B",
      "spotifyId": "57LYzLEk2LcFghVwuWbcuS",
      "popularity": 78,
      "popularityDelta": 0,
      "followers": 8523660,
      "monthlyListeners": 18394911,
      "listenersSource": "calibrated-proxy",
      "image": "https://i.scdn.co/image/ab6761610000e5eb7dccb6280ed3402110d43ce3",
      "fairPrice": 0.67,
      "price": 0.67,
      "chg24h": 0.0,
      "volatility30d": 0.0,
      "volume": 1752,
      "youtube": {
        "subscribers": 1770,
        "views": 940097146,
        "videos": 413
      },
      "youtubeViews": 940097146,
      "youtubeSubs": 1770,
      "youtubeBoost": 0.1338,
      "chartPositions": null,
      "chartBoost": 0.0,
      "popularityBoost": 0.084
    },
    {
      "ticker": "BFRY",
      "name": "Brent Faiyaz",
      "genre": "R&B",
      "spotifyId": "3tlXnStJ1fFhdScmQeLpuG",
      "popularity": 84,
      "popularityDelta": 0,
      "followers": 8605123,
      "monthlyListeners": 23010959,
      "listenersSource": "calibrated-proxy",
      "image": "https://i.scdn.co/image/ab6761610000e5eb582fbf712f5b6a9bf65d9b84",
      "fairPrice": 0.89,
      "price": 0.9,
      "chg24h": -1.1,
      "volatility30d": 0.004,
      "volume": 1760,
      "youtube": {
        "subscribers": 1970000,
        "views": 1419440423,
        "videos": 176
      },
      "youtubeViews": 1419440423,
      "youtubeSubs": 1970000,
      "youtubeBoost": 0.1936,
      "chartPositions": null,
      "chartBoost": 0.0,
      "popularityBoost": 0.102
    },
    {
      "ticker": "PRTY",
      "name": "PartyNextDoor",
      "genre": "R&B",
      "spotifyId": "2HPaUgqeutzr3jx5a9WyDV",
      "popularity": 85,
      "popularityDelta": 0,
      "followers": 11382085,
      "monthlyListeners": 28441554,
      "listenersSource": "calibrated-proxy",
      "image": "https://i.scdn.co/image/ab6761610000e5eb957320981e31e862bc2fb844",
      "fairPrice": 1.12,
      "price": 1.12,
      "chg24h": 0.0,
      "volatility30d": 0.0,
      "volume": 2024,
      "youtube": {
        "subscribers": 2420000,
        "views": 2226171475,
        "videos": 205
      },
      "youtubeViews": 2226171475,
      "youtubeSubs": 2420000,
      "youtubeBoost": 0.206,
      "chartPositions": null,
      "chartBoost": 0.0,
      "popularityBoost": 0.105
    },
    {
      "ticker": "GVON",
      "name": "Giveon",
      "genre": "R&B",
      "spotifyId": "4fxd5Ee7UefO4CUXgwJ7IP",
      "popularity": 80,
      "popularityDelta": 0,
      "followers": 5901647,
      "monthlyListeners": 29854662,
      "listenersSource": "calibrated-proxy",
      "image": "https://i.scdn.co/image/ab6761610000e5eb48769fa9ef3b5f24af90a09d",
      "fairPrice": 1.17,
      "price": 1.17,
      "chg24h": 1.74,
      "volatility30d": 0.007,
      "volume": 1458,
      "youtube": {
        "subscribers": 3450000,
        "views": 2278600608,
        "videos": 21
      },
      "youtubeViews": 2278600608,
      "youtubeSubs": 3450000,
      "youtubeBoost": 0.2126,
      "chartPositions": null,
      "chartBoost": 0.0,
      "popularityBoost": 0.09
    },
    {
      "ticker": "JHEN",
      "name": "Jhen\u00e9 Aiko",
      "genre": "R&B",
      "spotifyId": "5ZS223C6JyBfXasXxrRqOk",
      "popularity": 79,
      "popularityDelta": 0,
      "followers": 10118962,
      "monthlyListeners": 13719289,
      "listenersSource": "calibrated-proxy",
      "image": "https://i.scdn.co/image/ab6761610000e5ebebd0610816b0a89f40cdb4c2",
      "fairPrice": 0.54,
      "price": 0.55,
      "chg24h": 0.0,
      "volatility30d": 0.0,
      "volume": 1909,
      "youtube": {
        "subscribers": 3940000,
        "views": 3289606941,
        "videos": 77
      },
      "youtubeViews": 3289606941,
      "youtubeSubs": 3940000,
      "youtubeBoost": 0.2221,
      "chartPositions": null,
      "chartBoost": 0.0,
      "popularityBoost": 0.087
    },
    {
      "ticker": "KHLN",
      "name": "Kehlani",
      "genre": "R&B",
      "spotifyId": "0cGUm45nv7Z6M6qdXYQGTX",
      "popularity": 82,
      "popularityDelta": 0,
      "followers": 9376947,
      "monthlyListeners": 29913399,
      "listenersSource": "calibrated-proxy",
      "image": "https://i.scdn.co/image/ab6761610000e5ebcf865d7d399a41e1bd036149",
      "fairPrice": 1.39,
      "price": 1.38,
      "chg24h": 0.0,
      "volatility30d": 0.002,
      "volume": 1837,
      "youtube": {
        "subscribers": 4610000,
        "views": 2815652541,
        "videos": 276
      },
      "youtubeViews": 2815652541,
      "youtubeSubs": 4610000,
      "youtubeBoost": 0.2218,
      "chartPositions": {
        "hot100": 10
      },
      "chartBoost": 0.2275,
      "popularityBoost": 0.096
    },
    {
      "ticker": "DCSR",
      "name": "Daniel Caesar",
      "genre": "R&B",
      "spotifyId": "20wkVLutqVOYrc0kxFs7rA",
      "popularity": 88,
      "popularityDelta": 0,
      "followers": 13953081,
      "monthlyListeners": 45364257,
      "listenersSource": "calibrated-proxy",
      "image": "https://i.scdn.co/image/ab6761610000e5ebe4d94f7cbebb17504c25d419",
      "fairPrice": 1.79,
      "price": 1.79,
      "chg24h": 0.0,
      "volatility30d": 0.0,
      "volume": 2241,
      "youtube": {
        "subscribers": 2750000,
        "views": 1408804966,
        "videos": 26
      },
      "youtubeViews": 1408804966,
      "youtubeSubs": 2750000,
      "youtubeBoost": 0.1993,
      "chartPositions": null,
      "chartBoost": 0.0,
      "popularityBoost": 0.114
    },
    {
      "ticker": "BNNY",
      "name": "Bad Bunny",
      "genre": "Latin",
      "spotifyId": "4q3ewBCX7sLwd24euuV69X",
      "popularity": 100,
      "popularityDelta": 0,
      "followers": 115852366,
      "monthlyListeners": 101382405,
      "listenersSource": "calibrated-proxy",
      "image": "https://i.scdn.co/image/ab6761610000e5eb81f47f44084e0a09b5f0fa13",
      "fairPrice": 4.41,
      "price": 4.42,
      "chg24h": 0.0,
      "volatility30d": 0.01,
      "volume": 6458,
      "youtube": {
        "subscribers": 52800000,
        "views": 47321487743,
        "videos": 190
      },
      "youtubeViews": 47321487743,
      "youtubeSubs": 52800000,
      "youtubeBoost": 0.3,
      "chartPositions": null,
      "chartBoost": 0.0,
      "popularityBoost": 0.15
    },
    {
      "ticker": "PESO",
      "name": "Peso Pluma",
      "genre": "Latin",
      "spotifyId": "12GqGscKJx3aE4t07u7eVZ",
      "popularity": 93,
      "popularityDelta": 0,
      "followers": 27765001,
      "monthlyListeners": 47078336,
      "listenersSource": "calibrated-proxy",
      "image": "https://i.scdn.co/image/ab6761610000e5ebe5283f5b671cf618b82a2696",
      "fairPrice": 1.96,
      "price": 1.96,
      "chg24h": 0.0,
      "volatility30d": 0.0,
      "volume": 3162,
      "youtube": {
        "subscribers": 9200000,
        "views": 11962619792,
        "videos": 285
      },
      "youtubeViews": 11962619792,
      "youtubeSubs": 9200000,
      "youtubeBoost": 0.2621,
      "chartPositions": null,
      "chartBoost": 0.0,
      "popularityBoost": 0.129
    },
    {
      "ticker": "ROSA",
      "name": "Rosal\u00eda",
      "genre": "Latin",
      "spotifyId": "7ltDVBr6mKbRvohxheJ9h1",
      "popularity": 84,
      "popularityDelta": 0,
      "followers": 9702820,
      "monthlyListeners": 31027678,
      "listenersSource": "calibrated-proxy",
      "image": "https://i.scdn.co/image/ab6761610000e5eb9354faf80eb87961466edfbf",
      "fairPrice": 1.27,
      "price": 1.27,
      "chg24h": 0.0,
      "volatility30d": 0.0,
      "volume": 1869,
      "youtube": {
        "subscribers": 12200000,
        "views": 7299321580,
        "videos": 38
      },
      "youtubeViews": 7299321580,
      "youtubeSubs": 12200000,
      "youtubeBoost": 0.2573,
      "chartPositions": null,
      "chartBoost": 0.0,
      "popularityBoost": 0.102
    },
    {
      "ticker": "KROL",
      "name": "Karol G",
      "genre": "Latin",
      "spotifyId": "790FomKkXshlbRYZFtlgla",
      "popularity": 90,
      "popularityDelta": 0,
      "followers": 64485326,
      "monthlyListeners": 54644865,
      "listenersSource": "calibrated-proxy",
      "image": "https://i.scdn.co/image/ab6761610000e5eb66041ce9eb4497057cbc3496",
      "fairPrice": 2.35,
      "price": 2.34,
      "chg24h": 0.43,
      "volatility30d": 0.004,
      "volume": 4818,
      "youtube": {
        "subscribers": 41100000,
        "views": 33188202322,
        "videos": 166
      },
      "youtubeViews": 33188202322,
      "youtubeSubs": 41100000,
      "youtubeBoost": 0.3,
      "chartPositions": {
        "hot100": 96
      },
      "chartBoost": 0.0125,
      "popularityBoost": 0.12
    },
    {
      "ticker": "FEID",
      "name": "Feid",
      "genre": "Latin",
      "spotifyId": "2LRoIwlKmHjgvigdNGBHNo",
      "popularity": 89,
      "popularityDelta": 0,
      "followers": 20156291,
      "monthlyListeners": 37643889,
      "listenersSource": "calibrated-proxy",
      "image": "https://i.scdn.co/image/ab6761610000e5eb7e529f4ad13f86c69962cb12",
      "fairPrice": 1.55,
      "price": 1.55,
      "chg24h": 0.0,
      "volatility30d": 0.0,
      "volume": 2694,
      "youtube": {
        "subscribers": 7170000,
        "views": 11551508612,
        "videos": 188
      },
      "youtubeViews": 11551508612,
      "youtubeSubs": 7170000,
      "youtubeBoost": 0.257,
      "chartPositions": null,
      "chartBoost": 0.0,
      "popularityBoost": 0.117
    },
    {
      "ticker": "RAUW",
      "name": "Rauw Alejandro",
      "genre": "Latin",
      "spotifyId": "1mcTU81TzQhprhouKaTkpq",
      "popularity": 90,
      "popularityDelta": 0,
      "followers": 33771633,
      "monthlyListeners": 53457118,
      "listenersSource": "calibrated-proxy",
      "image": "https://i.scdn.co/image/ab6761610000e5eb6d72db3fd29576caa9cb821f",
      "fairPrice": 2.24,
      "price": 2.25,
      "chg24h": 0.0,
      "volatility30d": 0.0,
      "volume": 3487,
      "youtube": {
        "subscribers": 15400000,
        "views": 18538085388,
        "videos": 176
      },
      "youtubeViews": 18538085388,
      "youtubeSubs": 15400000,
      "youtubeBoost": 0.2796,
      "chartPositions": null,
      "chartBoost": 0.0,
      "popularityBoost": 0.12
    },
    {
      "ticker": "MYKE",
      "name": "Myke Towers",
      "genre": "Latin",
      "spotifyId": "7iK8PXO48WeuP03g8YR51W",
      "popularity": 88,
      "popularityDelta": 0,
      "followers": 24002592,
      "monthlyListeners": 39913910,
      "listenersSource": "calibrated-proxy",
      "image": "https://i.scdn.co/image/ab6761610000e5eb8372345609bebaf1e948ef7f",
      "fairPrice": 1.66,
      "price": 1.65,
      "chg24h": 0.0,
      "volatility30d": 0.0,
      "volume": 2940,
      "youtube": {
        "subscribers": 14500000,
        "views": 13698648765,
        "videos": 1291
      },
      "youtubeViews": 13698648765,
      "youtubeSubs": 14500000,
      "youtubeBoost": 0.2726,
      "chartPositions": null,
      "chartBoost": 0.0,
      "popularityBoost": 0.114
    },
    {
      "ticker": "OZNA",
      "name": "Ozuna",
      "genre": "Latin",
      "spotifyId": "1i8SpTcr7yvPOmcqrbnVXY",
      "popularity": 89,
      "popularityDelta": 0,
      "followers": 40759626,
      "monthlyListeners": 50884317,
      "listenersSource": "calibrated-proxy",
      "image": "https://i.scdn.co/image/ab6761610000e5eb1c4284179078e2529b1630e2",
      "fairPrice": 2.16,
      "price": 2.17,
      "chg24h": 0.0,
      "volatility30d": 0.0,
      "volume": 3831,
      "youtube": {
        "subscribers": 38100000,
        "views": 28841512286,
        "videos": 292
      },
      "youtubeViews": 28841512286,
      "youtubeSubs": 38100000,
      "youtubeBoost": 0.3,
      "chartPositions": null,
      "chartBoost": 0.0,
      "popularityBoost": 0.117
    },
    {
      "ticker": "JBLV",
      "name": "J Balvin",
      "genre": "Latin",
      "spotifyId": "1vyhD5VmyZ7KMfW5gqLgo5",
      "popularity": 90,
      "popularityDelta": 0,
      "followers": 40875225,
      "monthlyListeners": 73387379,
      "listenersSource": "calibrated-proxy",
      "image": "https://i.scdn.co/image/ab6761610000e5eb0405b03342c2e56751b9923d",
      "fairPrice": 3.13,
      "price": 3.13,
      "chg24h": 0.0,
      "volatility30d": 0.0,
      "volume": 3836,
      "youtube": {
        "subscribers": 35200000,
        "views": 27656395699,
        "videos": 390
      },
      "youtubeViews": 27656395699,
      "youtubeSubs": 35200000,
      "youtubeBoost": 0.3,
      "chartPositions": null,
      "chartBoost": 0.0,
      "popularityBoost": 0.12
    },
    {
      "ticker": "MLMA",
      "name": "Maluma",
      "genre": "Latin",
      "spotifyId": "1r4hJ1h58CWwUQe3MxPuau",
      "popularity": 87,
      "popularityDelta": 0,
      "followers": 40513906,
      "monthlyListeners": 47757792,
      "listenersSource": "calibrated-proxy",
      "image": "https://i.scdn.co/image/ab6761610000e5eb1b0d196ca84f4a0d076b4570",
      "fairPrice": 2.02,
      "price": 2.01,
      "chg24h": 0.0,
      "volatility30d": 0.005,
      "volume": 3819,
      "youtube": {
        "subscribers": 30900000,
        "views": 26831536394,
        "videos": 154
      },
      "youtubeViews": 26831536394,
      "youtubeSubs": 30900000,
      "youtubeBoost": 0.2989,
      "chartPositions": null,
      "chartBoost": 0.0,
      "popularityBoost": 0.111
    },
    {
      "ticker": "ANUL",
      "name": "Anuel AA",
      "genre": "Latin",
      "spotifyId": "2R21vXR83lH98kGeO99Y66",
      "popularity": 90,
      "popularityDelta": 0,
      "followers": 48516963,
      "monthlyListeners": 44101919,
      "listenersSource": "calibrated-proxy",
      "image": "https://i.scdn.co/image/ab6761610000e5eba23ceb177745632b517cb7b2",
      "fairPrice": 1.49,
      "price": 1.48,
      "chg24h": 0.0,
      "volatility30d": 0.0,
      "volume": 4179,
      "youtube": {
        "subscribers": 4670,
        "views": 1359028,
        "videos": 38
      },
      "youtubeViews": 1359028,
      "youtubeSubs": 4670,
      "youtubeBoost": 0.006,
      "chartPositions": null,
      "chartBoost": 0.0,
      "popularityBoost": 0.12
    },
    {
      "ticker": "SBYA",
      "name": "Sebasti\u00e1n Yatra",
      "genre": "Latin",
      "spotifyId": "07YUOmWljBTXwIseAUd9TW",
      "popularity": 80,
      "popularityDelta": 0,
      "followers": 24851556,
      "monthlyListeners": 24128376,
      "listenersSource": "calibrated-proxy",
      "image": "https://i.scdn.co/image/ab6761610000e5eb90671876e11f39f835ececa4",
      "fairPrice": 0.89,
      "price": 0.89,
      "chg24h": 0.0,
      "volatility30d": 0.0,
      "volume": 2991,
      "youtube": {
        "subscribers": 12600,
        "views": 1711027875,
        "videos": 1247
      },
      "youtubeViews": 1711027875,
      "youtubeSubs": 12600,
      "youtubeBoost": 0.1455,
      "chartPositions": null,
      "chartBoost": 0.0,
      "popularityBoost": 0.09
    },
    {
      "ticker": "QUVD",
      "name": "Quevedo",
      "genre": "Latin",
      "spotifyId": "52iwsT98xCoGgiGntTiR7K",
      "popularity": 86,
      "popularityDelta": 0,
      "followers": 6911349,
      "monthlyListeners": 29276474,
      "listenersSource": "calibrated-proxy",
      "image": "https://i.scdn.co/image/ab6761610000e5eb6ba600ad0f41d8a3aa3f53b2",
      "fairPrice": 1.09,
      "price": 1.08,
      "chg24h": 0.0,
      "volatility30d": 0.0,
      "volume": 1577,
      "youtube": {
        "subscribers": 718,
        "views": 749541336,
        "videos": 131
      },
      "youtubeViews": 749541336,
      "youtubeSubs": 718,
      "youtubeBoost": 0.1294,
      "chartPositions": null,
      "chartBoost": 0.0,
      "popularityBoost": 0.108
    },
    {
      "ticker": "FRZA",
      "name": "Fuerza Regida",
      "genre": "Latin",
      "spotifyId": "0ys2OFYzWYB5hRDLCsBqxt",
      "popularity": 93,
      "popularityDelta": 0,
      "followers": 25461679,
      "monthlyListeners": 48030911,
      "listenersSource": "calibrated-proxy",
      "image": "https://i.scdn.co/image/ab6761610000e5ebce436c411ab2436c7ab2c04d",
      "fairPrice": 2.0,
      "price": 2.0,
      "chg24h": 0.0,
      "volatility30d": 0.0,
      "volume": 3028,
      "youtube": {
        "subscribers": 6720000,
        "views": 11835191147,
        "videos": 135
      },
      "youtubeViews": 11835191147,
      "youtubeSubs": 6720000,
      "youtubeBoost": 0.2564,
      "chartPositions": null,
      "chartBoost": 0.0,
      "popularityBoost": 0.129
    },
    {
      "ticker": "JRRH",
      "name": "Junior H",
      "genre": "Latin",
      "spotifyId": "7Gi6gjaWy3DxyilpF1a8Is",
      "popularity": 90,
      "popularityDelta": 0,
      "followers": 32831416,
      "monthlyListeners": 30339512,
      "listenersSource": "calibrated-proxy",
      "image": "https://i.scdn.co/image/ab6761610000e5eb5fbe9b7dc7d9a2295bd6022c",
      "fairPrice": 1.24,
      "price": 1.25,
      "chg24h": 0.0,
      "volatility30d": 0.0,
      "volume": 3438,
      "youtube": {
        "subscribers": 3960000,
        "views": 7662003704,
        "videos": 24
      },
      "youtubeViews": 7662003704,
      "youtubeSubs": 3960000,
      "youtubeBoost": 0.2387,
      "chartPositions": null,
      "chartBoost": 0.0,
      "popularityBoost": 0.12
    },
    {
      "ticker": "TYLA",
      "name": "Tyla",
      "genre": "Afropop",
      "spotifyId": "3SozjO3Lat463tQICI9LcE",
      "popularity": 81,
      "popularityDelta": 0,
      "followers": 4839289,
      "monthlyListeners": 35056777,
      "listenersSource": "calibrated-proxy",
      "image": "https://i.scdn.co/image/ab6761610000e5eb69719e4164b893213a525d25",
      "fairPrice": 1.43,
      "price": 1.44,
      "chg24h": 0.0,
      "volatility30d": 0.0,
      "volume": 1320,
      "youtube": {
        "subscribers": 5850000,
        "views": 2537509995,
        "videos": 166
      },
      "youtubeViews": 2537509995,
      "youtubeSubs": 5850000,
      "youtubeBoost": 0.2239,
      "chartPositions": {
        "hot100": 84
      },
      "chartBoost": 0.0425,
      "popularityBoost": 0.093
    },
    {
      "ticker": "REMA",
      "name": "Rema",
      "genre": "Afropop",
      "spotifyId": "46pWGuE3dSwY3bMMXGBvVS",
      "popularity": 80,
      "popularityDelta": 0,
      "followers": 10691529,
      "monthlyListeners": 24624730,
      "listenersSource": "calibrated-proxy",
      "image": "https://i.scdn.co/image/ab6761610000e5ebf4626451ff59c5989a1af18d",
      "fairPrice": 0.97,
      "price": 0.96,
      "chg24h": 0.0,
      "volatility30d": 0.005,
      "volume": 1962,
      "youtube": {
        "subscribers": 5450000,
        "views": 2468781832,
        "videos": 194
      },
      "youtubeViews": 2468781832,
      "youtubeSubs": 5450000,
      "youtubeBoost": 0.2221,
      "chartPositions": null,
      "chartBoost": 0.0,
      "popularityBoost": 0.09
    },
    {
      "ticker": "AYRA",
      "name": "Ayra Starr",
      "genre": "Afropop",
      "spotifyId": "3ZpEKRjHaHANcpk10u6Ntq",
      "popularity": 76,
      "popularityDelta": 0,
      "followers": 6867317,
      "monthlyListeners": 16039306,
      "listenersSource": "calibrated-proxy",
      "image": "https://i.scdn.co/image/ab6761610000e5eb8bfd832e0547c4acabe6e67c",
      "fairPrice": 0.57,
      "price": 0.57,
      "chg24h": 0.0,
      "volatility30d": 0.0,
      "volume": 1572,
      "youtube": {
        "subscribers": 4510,
        "views": 207193667,
        "videos": 130
      },
      "youtubeViews": 207193667,
      "youtubeSubs": 4510,
      "youtubeBoost": 0.1042,
      "chartPositions": null,
      "chartBoost": 0.0,
      "popularityBoost": 0.078
    },
    {
      "ticker": "BRNA",
      "name": "Burna Boy",
      "genre": "Afropop",
      "spotifyId": "3wcj11K77LjEY1PkEazffa",
      "popularity": 82,
      "popularityDelta": 0,
      "followers": 16218752,
      "monthlyListeners": 24915247,
      "listenersSource": "calibrated-proxy",
      "image": "https://i.scdn.co/image/ab6761610000e5ebb4e44d0f4e3e47af2cf06f3f",
      "fairPrice": 0.99,
      "price": 0.99,
      "chg24h": 0.0,
      "volatility30d": 0.0,
      "volume": 2416,
      "youtube": {
        "subscribers": 5820000,
        "views": 3828807330,
        "videos": 320
      },
      "youtubeViews": 3828807330,
      "youtubeSubs": 5820000,
      "youtubeBoost": 0.2318,
      "chartPositions": null,
      "chartBoost": 0.0,
      "popularityBoost": 0.096
    },
    {
      "ticker": "WZKD",
      "name": "Wizkid",
      "genre": "Afropop",
      "spotifyId": "3tVQdUvClmAT7URs9V3rsp",
      "popularity": 83,
      "popularityDelta": 0,
      "followers": 11350721,
      "monthlyListeners": 18301903,
      "listenersSource": "calibrated-proxy",
      "image": "https://i.scdn.co/image/ab6761610000e5ebe6ef803356b45ee5a9fa7a8a",
      "fairPrice": 0.67,
      "price": 0.68,
      "chg24h": 0.0,
      "volatility30d": 0.0,
      "volume": 2021,
      "youtube": {
        "subscribers": 25500,
        "views": 492741567,
        "videos": 250
      },
      "youtubeViews": 492741567,
      "youtubeSubs": 25500,
      "youtubeBoost": 0.1212,
      "chartPositions": null,
      "chartBoost": 0.0,
      "popularityBoost": 0.099
    },
    {
      "ticker": "DAVD",
      "name": "Davido",
      "genre": "Afropop",
      "spotifyId": "0Y3agQaa6g2r0YmHPOO9rh",
      "popularity": 76,
      "popularityDelta": 0,
      "followers": 10827798,
      "monthlyListeners": 9762343,
      "listenersSource": "calibrated-proxy",
      "image": "https://i.scdn.co/image/ab6761610000e5eb057fdb13352beee124b79051",
      "fairPrice": 0.35,
      "price": 0.34,
      "chg24h": 0.0,
      "volatility30d": 0.0,
      "volume": 1974,
      "youtube": {
        "subscribers": 14000,
        "views": 347090769,
        "videos": 193
      },
      "youtubeViews": 347090769,
      "youtubeSubs": 14000,
      "youtubeBoost": 0.1143,
      "chartPositions": null,
      "chartBoost": 0.0,
      "popularityBoost": 0.078
    },
    {
      "ticker": "ASKE",
      "name": "Asake",
      "genre": "Afropop",
      "spotifyId": "3a1tBryiczPAZpgoZN9Rzg",
      "popularity": 83,
      "popularityDelta": 0,
      "followers": 8993605,
      "monthlyListeners": 8934247,
      "listenersSource": "calibrated-proxy",
      "image": "https://i.scdn.co/image/ab6761610000e5ebff54cbafa23b728b49954587",
      "fairPrice": 0.34,
      "price": 0.34,
      "chg24h": 0.0,
      "volatility30d": 0.0,
      "volume": 1799,
      "youtube": {
        "subscribers": 1990000,
        "views": 1008263009,
        "videos": 52
      },
      "youtubeViews": 1008263009,
      "youtubeSubs": 1990000,
      "youtubeBoost": 0.1871,
      "chartPositions": null,
      "chartBoost": 0.0,
      "popularityBoost": 0.099
    },
    {
      "ticker": "CKAY",
      "name": "CKay",
      "genre": "Afropop",
      "spotifyId": "048LktY5zMnakWq7PTtFrz",
      "popularity": 70,
      "popularityDelta": 0,
      "followers": 2044037,
      "monthlyListeners": 10209965,
      "listenersSource": "calibrated-proxy",
      "image": "https://i.scdn.co/image/ab6761610000e5ebe7e497134d99ab17498988fb",
      "fairPrice": 0.39,
      "price": 0.39,
      "chg24h": 0.0,
      "volatility30d": 0.0,
      "volume": 858,
      "youtube": {
        "subscribers": 4340000,
        "views": 1825151591,
        "videos": 153
      },
      "youtubeViews": 1825151591,
      "youtubeSubs": 4340000,
      "youtubeBoost": 0.2123,
      "chartPositions": null,
      "chartBoost": 0.0,
      "popularityBoost": 0.06
    },
    {
      "ticker": "TEMS",
      "name": "Tems",
      "genre": "Afropop",
      "spotifyId": "687cZJR45JO7jhk1LHIbgq",
      "popularity": 84,
      "popularityDelta": 0,
      "followers": 4414668,
      "monthlyListeners": 45117907,
      "listenersSource": "calibrated-proxy",
      "image": "https://i.scdn.co/image/ab6761610000e5eb22d7d6f8981c7a27bf68a382",
      "fairPrice": 1.84,
      "price": 1.85,
      "chg24h": 0.0,
      "volatility30d": 0.0,
      "volume": 1261,
      "youtube": {
        "subscribers": 1560000,
        "views": 840604293,
        "videos": 62
      },
      "youtubeViews": 840604293,
      "youtubeSubs": 1560000,
      "youtubeBoost": 0.1793,
      "chartPositions": {
        "hot100": 69
      },
      "chartBoost": 0.08,
      "popularityBoost": 0.102
    },
    {
      "ticker": "FRBY",
      "name": "Fireboy DML",
      "genre": "Afropop",
      "spotifyId": "75VKfyoBlkmrJFDqo1o2VY",
      "popularity": 72,
      "popularityDelta": 0,
      "followers": 5296295,
      "monthlyListeners": 8657853,
      "listenersSource": "calibrated-proxy",
      "image": "https://i.scdn.co/image/ab6761610000e5ebf0da9bd951adbb3749b40904",
      "fairPrice": 0.31,
      "price": 0.3,
      "chg24h": 3.45,
      "volatility30d": 0.004,
      "volume": 1381,
      "youtube": {
        "subscribers": 1020,
        "views": 268698862,
        "videos": 122
      },
      "youtubeViews": 268698862,
      "youtubeSubs": 1020,
      "youtubeBoost": 0.1093,
      "chartPositions": null,
      "chartBoost": 0.0,
      "popularityBoost": 0.066
    },
    {
      "ticker": "BILL",
      "name": "Billie Eilish",
      "genre": "Alt",
      "spotifyId": "6qqNVTkY8uBg9cP3Jd7DAH",
      "popularity": 92,
      "popularityDelta": 0,
      "followers": 126221632,
      "monthlyListeners": 84555871,
      "listenersSource": "calibrated-proxy",
      "image": "https://i.scdn.co/image/ab6761610000e5eb4a21b4760d2ecb7b0dcdc8da",
      "fairPrice": 3.29,
      "price": 3.29,
      "chg24h": 0.61,
      "volatility30d": 0.007,
      "volume": 6741,
      "youtube": {
        "subscribers": 13500,
        "views": 5735368592,
        "videos": 795
      },
      "youtubeViews": 5735368592,
      "youtubeSubs": 13500,
      "youtubeBoost": 0.1691,
      "chartPositions": null,
      "chartBoost": 0.0,
      "popularityBoost": 0.126
    },
    {
      "ticker": "LANA",
      "name": "Lana Del Rey",
      "genre": "Alt",
      "spotifyId": "00FQb4jTyendYWaN8pK0wa",
      "popularity": 91,
      "popularityDelta": 0,
      "followers": 57025329,
      "monthlyListeners": 65687476,
      "listenersSource": "calibrated-proxy",
      "image": "https://i.scdn.co/image/ab6761610000e5ebb99cacf8acd5378206767261",
      "fairPrice": 2.75,
      "price": 2.75,
      "chg24h": 0.0,
      "volatility30d": 0.0,
      "volume": 4531,
      "youtube": {
        "subscribers": 18600000,
        "views": 11315850254,
        "videos": 48
      },
      "youtubeViews": 11315850254,
      "youtubeSubs": 18600000,
      "youtubeBoost": 0.2732,
      "chartPositions": null,
      "chartBoost": 0.0,
      "popularityBoost": 0.123
    },
    {
      "ticker": "HZER",
      "name": "Hozier",
      "genre": "Alt",
      "spotifyId": "2FXC3k01G6Gw61bmprjgqS",
      "popularity": 84,
      "popularityDelta": 0,
      "followers": 9498825,
      "monthlyListeners": 42039900,
      "listenersSource": "calibrated-proxy",
      "image": "https://i.scdn.co/image/ab6761610000e5ebad85a585103dfc2f3439119a",
      "fairPrice": 1.68,
      "price": 1.67,
      "chg24h": 0.0,
      "volatility30d": 0.0,
      "volume": 1849,
      "youtube": {
        "subscribers": 4700000,
        "views": 4067273324,
        "videos": 209
      },
      "youtubeViews": 4067273324,
      "youtubeSubs": 4700000,
      "youtubeBoost": 0.2293,
      "chartPositions": null,
      "chartBoost": 0.0,
      "popularityBoost": 0.102
    },
    {
      "ticker": "ARCT",
      "name": "Arctic Monkeys",
      "genre": "Alt",
      "spotifyId": "7Ln80lUS6He07XvHI8qqHH",
      "popularity": 87,
      "popularityDelta": 0,
      "followers": 34288050,
      "monthlyListeners": 55412918,
      "listenersSource": "calibrated-proxy",
      "image": "https://i.scdn.co/image/ab6761610000e5eb7da39dea0a72f581535fb11f",
      "fairPrice": 2.27,
      "price": 2.26,
      "chg24h": 0.0,
      "volatility30d": 0.0,
      "volume": 3513,
      "youtube": {
        "subscribers": 9400000,
        "views": 7561881233,
        "videos": 90
      },
      "youtubeViews": 7561881233,
      "youtubeSubs": 9400000,
      "youtubeBoost": 0.2535,
      "chartPositions": null,
      "chartBoost": 0.0,
      "popularityBoost": 0.111
    },
    {
      "ticker": "LRDE",
      "name": "Lorde",
      "genre": "Alt",
      "spotifyId": "163tK9Wjr9P9DmM0AVK7lm",
      "popularity": 81,
      "popularityDelta": 0,
      "followers": 10831579,
      "monthlyListeners": 27162351,
      "listenersSource": "calibrated-proxy",
      "image": "https://i.scdn.co/image/ab6761610000e5ebaa69380a8d5203257611662d",
      "fairPrice": 1.07,
      "price": 1.06,
      "chg24h": 0.0,
      "volatility30d": 0.0,
      "volume": 1975,
      "youtube": {
        "subscribers": 5180000,
        "views": 2773328930,
        "videos": 14
      },
      "youtubeViews": 2773328930,
      "youtubeSubs": 5180000,
      "youtubeBoost": 0.2235,
      "chartPositions": null,
      "chartBoost": 0.0,
      "popularityBoost": 0.093
    },
    {
      "ticker": "TAME",
      "name": "Tame Impala",
      "genre": "Alt",
      "spotifyId": "5INjqkS1o8h1imAzPqGZBb",
      "popularity": 89,
      "popularityDelta": 0,
      "followers": 10902301,
      "monthlyListeners": 64388990,
      "listenersSource": "calibrated-proxy",
      "image": "https://i.scdn.co/image/ab6761610000e5ebe412a782245eb20d9626c601",
      "fairPrice": 2.98,
      "price": 2.98,
      "chg24h": 0.0,
      "volatility30d": 0.002,
      "volume": 1981,
      "youtube": {
        "subscribers": 3410000,
        "views": 2725871912,
        "videos": 45
      },
      "youtubeViews": 2725871912,
      "youtubeSubs": 3410000,
      "youtubeBoost": 0.2159,
      "chartPositions": {
        "hot100": 18
      },
      "chartBoost": 0.2075,
      "popularityBoost": 0.117
    },
    {
      "ticker": "FTNS",
      "name": "Fontaines D.C.",
      "genre": "Alt",
      "spotifyId": "3SXwqSqAoBz9WCI9PDQzY6",
      "popularity": 73,
      "popularityDelta": 0,
      "followers": 1350418,
      "monthlyListeners": 6826768,
      "listenersSource": "calibrated-proxy",
      "image": "https://i.scdn.co/image/ab6761610000e5ebc4b9cd69cf77ce41487dd69a",
      "fairPrice": 0.23,
      "price": 0.23,
      "chg24h": 0.0,
      "volatility30d": 0.0,
      "volume": 697,
      "youtube": {
        "subscribers": 206,
        "views": 48142894,
        "videos": 183
      },
      "youtubeViews": 48142894,
      "youtubeSubs": 206,
      "youtubeBoost": 0.0757,
      "chartPositions": null,
      "chartBoost": 0.0,
      "popularityBoost": 0.069
    },
    {
      "ticker": "MARI",
      "name": "The Mar\u00edas",
      "genre": "Indie",
      "spotifyId": "2sSGPbdZJkaSE2AbcGOACx",
      "popularity": 84,
      "popularityDelta": 0,
      "followers": 4916791,
      "monthlyListeners": 34254791,
      "listenersSource": "calibrated-proxy",
      "image": "https://i.scdn.co/image/ab6761610000e5ebaf586afa2b397f1288683a76",
      "fairPrice": 1.25,
      "price": 1.25,
      "chg24h": 0.0,
      "volatility30d": 0.0,
      "volume": 1330,
      "youtube": {
        "subscribers": 1880,
        "views": 420441999,
        "videos": 61
      },
      "youtubeViews": 420441999,
      "youtubeSubs": 1880,
      "youtubeBoost": 0.1181,
      "chartPositions": null,
      "chartBoost": 0.0,
      "popularityBoost": 0.102
    },
    {
      "ticker": "CLRO",
      "name": "Clairo",
      "genre": "Indie",
      "spotifyId": "3l0CmX0FuQjFxr8SK7Vqag",
      "popularity": 80,
      "popularityDelta": 0,
      "followers": 7088209,
      "monthlyListeners": 16762905,
      "listenersSource": "calibrated-proxy",
      "image": "https://i.scdn.co/image/ab6761610000e5eb4804c4a44c85afea1a72d1bd",
      "fairPrice": 0.6,
      "price": 0.59,
      "chg24h": 0.0,
      "volatility30d": 0.0,
      "volume": 1597,
      "youtube": {
        "subscribers": 1960,
        "views": 192248046,
        "videos": 69
      },
      "youtubeViews": 192248046,
      "youtubeSubs": 1960,
      "youtubeBoost": 0.1028,
      "chartPositions": null,
      "chartBoost": 0.0,
      "popularityBoost": 0.09
    },
    {
      "ticker": "BEAB",
      "name": "Beabadoobee",
      "genre": "Indie",
      "spotifyId": "35l9BRT7MXmM8bv2WDQiyB",
      "popularity": 81,
      "popularityDelta": 0,
      "followers": 7328692,
      "monthlyListeners": 22644193,
      "listenersSource": "calibrated-proxy",
      "image": "https://i.scdn.co/image/ab6761610000e5ebf40305a6273b3e0a514cc8da",
      "fairPrice": 0.86,
      "price": 0.86,
      "chg24h": 0.0,
      "volatility30d": 0.0,
      "volume": 1624,
      "youtube": {
        "subscribers": 2000000,
        "views": 586959518,
        "videos": 368
      },
      "youtubeViews": 586959518,
      "youtubeSubs": 2000000,
      "youtubeBoost": 0.1766,
      "chartPositions": null,
      "chartBoost": 0.0,
      "popularityBoost": 0.093
    },
    {
      "ticker": "MTSK",
      "name": "Mitski",
      "genre": "Indie",
      "spotifyId": "2uYWxilOVlUdk4oV9DvwqK",
      "popularity": 81,
      "popularityDelta": 0,
      "followers": 11685767,
      "monthlyListeners": 20249097,
      "listenersSource": "calibrated-proxy",
      "image": "https://i.scdn.co/image/ab6761610000e5eb16eec86fff40fa5ef0b57cef",
      "fairPrice": 0.79,
      "price": 0.8,
      "chg24h": 0.0,
      "volatility30d": 0.0,
      "volume": 2051,
      "youtube": {
        "subscribers": 2860000,
        "views": 1492919841,
        "videos": 213
      },
      "youtubeViews": 1492919841,
      "youtubeSubs": 2860000,
      "youtubeBoost": 0.2011,
      "chartPositions": null,
      "chartBoost": 0.0,
      "popularityBoost": 0.093
    },
    {
      "ticker": "PHBE",
      "name": "Phoebe Bridgers",
      "genre": "Indie",
      "spotifyId": "1r1uxoy19fzMxunt3ONAkG",
      "popularity": 78,
      "popularityDelta": 0,
      "followers": 3237776,
      "monthlyListeners": 11305019,
      "listenersSource": "calibrated-proxy",
      "image": "https://i.scdn.co/image/ab6761610000e5eb626686e362d30246e816cc5b",
      "fairPrice": 0.41,
      "price": 0.41,
      "chg24h": 0.0,
      "volatility30d": 0.0,
      "volume": 1080,
      "youtube": {
        "subscribers": 423000,
        "views": 213798635,
        "videos": 15
      },
      "youtubeViews": 213798635,
      "youtubeSubs": 423000,
      "youtubeBoost": 0.1299,
      "chartPositions": null,
      "chartBoost": 0.0,
      "popularityBoost": 0.084
    },
    {
      "ticker": "BOYG",
      "name": "boygenius",
      "genre": "Indie",
      "spotifyId": "1hLiboQ98IQWhpKeP9vRFw",
      "popularity": 65,
      "popularityDelta": 0,
      "followers": 1132601,
      "monthlyListeners": 3261438,
      "listenersSource": "calibrated-proxy",
      "image": "https://i.scdn.co/image/ab6761610000e5eb1a6373c01e8b86e289859f57",
      "fairPrice": 0.11,
      "price": 0.11,
      "chg24h": 0.0,
      "volatility30d": 0.0,
      "volume": 639,
      "youtube": {
        "subscribers": 171000,
        "views": 66924202,
        "videos": 30
      },
      "youtubeViews": 66924202,
      "youtubeSubs": 171000,
      "youtubeBoost": 0.0915,
      "chartPositions": null,
      "chartBoost": 0.0,
      "popularityBoost": 0.045
    },
    {
      "ticker": "FAYE",
      "name": "Faye Webster",
      "genre": "Indie",
      "spotifyId": "5szilpXHcwOqnyKLqGco5j",
      "popularity": 72,
      "popularityDelta": 0,
      "followers": 2429242,
      "monthlyListeners": 7734707,
      "listenersSource": "calibrated-proxy",
      "image": "https://i.scdn.co/image/ab6761610000e5eb4935804c2a7f4d6a22525607",
      "fairPrice": 0.27,
      "price": 0.27,
      "chg24h": 0.0,
      "volatility30d": 0.0,
      "volume": 935,
      "youtube": {
        "subscribers": 445,
        "views": 178369244,
        "videos": 50
      },
      "youtubeViews": 178369244,
      "youtubeSubs": 445,
      "youtubeBoost": 0.1013,
      "chartPositions": null,
      "chartBoost": 0.0,
      "popularityBoost": 0.066
    },
    {
      "ticker": "CGAS",
      "name": "Cigarettes After Sex",
      "genre": "Indie",
      "spotifyId": "1QAJqy2dA3ihHBFIHRphZj",
      "popularity": 85,
      "popularityDelta": 0,
      "followers": 18955116,
      "monthlyListeners": 29357684,
      "listenersSource": "calibrated-proxy",
      "image": "https://i.scdn.co/image/ab6761610000e5eb1c312be98c615df97ea79a30",
      "fairPrice": 1.16,
      "price": 1.15,
      "chg24h": 0.0,
      "volatility30d": 0.0,
      "volume": 2612,
      "youtube": {
        "subscribers": 4260000,
        "views": 1926840233,
        "videos": 64
      },
      "youtubeViews": 1926840233,
      "youtubeSubs": 4260000,
      "youtubeBoost": 0.213,
      "chartPositions": null,
      "chartBoost": 0.0,
      "popularityBoost": 0.105
    },
    {
      "ticker": "BTS",
      "name": "BTS",
      "genre": "K-Pop",
      "spotifyId": "3Nrfpe0tUJi4K4DXYWgMUX",
      "popularity": 98,
      "popularityDelta": 0,
      "followers": 85407548,
      "monthlyListeners": 39987814,
      "listenersSource": "calibrated-proxy",
      "image": "https://i.scdn.co/image/ab6761610000e5ebf80ec63ea7a0ef0fba60957d",
      "fairPrice": 1.94,
      "price": 1.94,
      "chg24h": -1.02,
      "volatility30d": 0.007,
      "volume": 5545,
      "youtube": {
        "subscribers": 84200000,
        "views": 27843610817,
        "videos": 3035
      },
      "youtubeViews": 27843610817,
      "youtubeSubs": 84200000,
      "youtubeBoost": 0.3,
      "chartPositions": {
        "hot100": 32
      },
      "chartBoost": 0.1725,
      "popularityBoost": 0.144
    },
    {
      "ticker": "BLPK",
      "name": "BLACKPINK",
      "genre": "K-Pop",
      "spotifyId": "41MozSoPIsD1dJM0CLPjZF",
      "popularity": 83,
      "popularityDelta": 0,
      "followers": 59101242,
      "monthlyListeners": 22925372,
      "listenersSource": "calibrated-proxy",
      "image": "https://i.scdn.co/image/ab6761610000e5eb623538b7014238c54ceee056",
      "fairPrice": 0.96,
      "price": 0.96,
      "chg24h": -1.03,
      "volatility30d": 0.004,
      "volume": 4613,
      "youtube": {
        "subscribers": 101000000,
        "views": 41756433903,
        "videos": 666
      },
      "youtubeViews": 41756433903,
      "youtubeSubs": 101000000,
      "youtubeBoost": 0.3,
      "chartPositions": null,
      "chartBoost": 0.0,
      "popularityBoost": 0.099
    },
    {
      "ticker": "NWJN",
      "name": "NewJeans",
      "genre": "K-Pop",
      "spotifyId": "6HvZYsbFfjnjFrWF950C9d",
      "popularity": 79,
      "popularityDelta": 0,
      "followers": 12819585,
      "monthlyListeners": 13766952,
      "listenersSource": "calibrated-proxy",
      "image": "https://i.scdn.co/image/ab6761610000e5eb8dae71b664393f38ba91f891",
      "fairPrice": 0.55,
      "price": 0.56,
      "chg24h": 0.0,
      "volatility30d": 0.0,
      "volume": 2148,
      "youtube": {
        "subscribers": 8360000,
        "views": 5082041387,
        "videos": 752
      },
      "youtubeViews": 5082041387,
      "youtubeSubs": 8360000,
      "youtubeBoost": 0.2437,
      "chartPositions": null,
      "chartBoost": 0.0,
      "popularityBoost": 0.087
    },
    {
      "ticker": "STRY",
      "name": "Stray Kids",
      "genre": "K-Pop",
      "spotifyId": "2dIgFjalVxs4ThymZ67YCE",
      "popularity": 86,
      "popularityDelta": 0,
      "followers": 23186823,
      "monthlyListeners": 10417840,
      "listenersSource": "calibrated-proxy",
      "image": "https://i.scdn.co/image/ab6761610000e5ebf9887d2c9288f0e50a3fd69f",
      "fairPrice": 0.43,
      "price": 0.43,
      "chg24h": 0.0,
      "volatility30d": 0.004,
      "volume": 2889,
      "youtube": {
        "subscribers": 23700000,
        "views": 11399425374,
        "videos": 2051
      },
      "youtubeViews": 11399425374,
      "youtubeSubs": 23700000,
      "youtubeBoost": 0.2775,
      "chartPositions": null,
      "chartBoost": 0.0,
      "popularityBoost": 0.108
    },
    {
      "ticker": "TWIC",
      "name": "TWICE",
      "genre": "K-Pop",
      "spotifyId": "7n2Ycct7Beij7Dj7meI4X0",
      "popularity": 82,
      "popularityDelta": 0,
      "followers": 24917338,
      "monthlyListeners": 16256071,
      "listenersSource": "calibrated-proxy",
      "image": "https://i.scdn.co/image/ab6761610000e5eb3d8820046fd455b38d644864",
      "fairPrice": 0.67,
      "price": 0.68,
      "chg24h": 0.0,
      "volatility30d": 0.0,
      "volume": 2995,
      "youtube": {
        "subscribers": 19200000,
        "views": 9128501839,
        "videos": 2483
      },
      "youtubeViews": 9128501839,
      "youtubeSubs": 19200000,
      "youtubeBoost": 0.2696,
      "chartPositions": null,
      "chartBoost": 0.0,
      "popularityBoost": 0.096
    },
    {
      "ticker": "GTTA",
      "name": "David Guetta",
      "genre": "Electronic",
      "spotifyId": "1Cs0zKBU1kc0i8ypK3B9ai",
      "popularity": 90,
      "popularityDelta": 0,
      "followers": 27926013,
      "monthlyListeners": 88966692,
      "listenersSource": "calibrated-proxy",
      "image": "https://i.scdn.co/image/ab6761610000e5ebf150017ca69c8793503c2d4f",
      "fairPrice": 3.77,
      "price": 3.76,
      "chg24h": 0.0,
      "volatility30d": 0.002,
      "volume": 3171,
      "youtube": {
        "subscribers": 27800000,
        "views": 23131815699,
        "videos": 1049
      },
      "youtubeViews": 23131815699,
      "youtubeSubs": 27800000,
      "youtubeBoost": 0.2942,
      "chartPositions": null,
      "chartBoost": 0.0,
      "popularityBoost": 0.12
    },
    {
      "ticker": "CHRS",
      "name": "Calvin Harris",
      "genre": "Electronic",
      "spotifyId": "7CajNmpbOovFoOoasH2HaY",
      "popularity": 88,
      "popularityDelta": 0,
      "followers": 23532588,
      "monthlyListeners": 76471498,
      "listenersSource": "calibrated-proxy",
      "image": "https://i.scdn.co/image/ab6761610000e5eb8ebba5e60113b48de8c11f6b",
      "fairPrice": 3.21,
      "price": 3.21,
      "chg24h": 0.0,
      "volatility30d": 0.002,
      "volume": 2911,
      "youtube": {
        "subscribers": 19600000,
        "views": 18895464645,
        "videos": 105
      },
      "youtubeViews": 18895464645,
      "youtubeSubs": 19600000,
      "youtubeBoost": 0.2841,
      "chartPositions": null,
      "chartBoost": 0.0,
      "popularityBoost": 0.114
    },
    {
      "ticker": "FRED",
      "name": "Fred again..",
      "genre": "Electronic",
      "spotifyId": "4oLeXFyACqeem2VImYeBFe",
      "popularity": 80,
      "popularityDelta": 0,
      "followers": 2593046,
      "monthlyListeners": 18471563,
      "listenersSource": "calibrated-proxy",
      "image": "https://i.scdn.co/image/ab6761610000e5eb381c41adc678e4ce864eb274",
      "fairPrice": 0.67,
      "price": 0.68,
      "chg24h": 0.0,
      "volatility30d": 0.0,
      "volume": 966,
      "youtube": {
        "subscribers": 469,
        "views": 284932949,
        "videos": 379
      },
      "youtubeViews": 284932949,
      "youtubeSubs": 469,
      "youtubeBoost": 0.1105,
      "chartPositions": null,
      "chartBoost": 0.0,
      "popularityBoost": 0.09
    },
    {
      "ticker": "SKRL",
      "name": "Skrillex",
      "genre": "Electronic",
      "spotifyId": "5he5w2lnU9x7JFhnwcekXX",
      "popularity": 79,
      "popularityDelta": 0,
      "followers": 7619238,
      "monthlyListeners": 30903629,
      "listenersSource": "calibrated-proxy",
      "image": "https://i.scdn.co/image/ab6761610000e5ebd94d5ea8008678a7b61f01b5",
      "fairPrice": 1.25,
      "price": 1.25,
      "chg24h": 0.0,
      "volatility30d": 0.004,
      "volume": 1656,
      "youtube": {
        "subscribers": 20400000,
        "views": 7443752614,
        "videos": 253
      },
      "youtubeViews": 7443752614,
      "youtubeSubs": 20400000,
      "youtubeBoost": 0.2666,
      "chartPositions": null,
      "chartBoost": 0.0,
      "popularityBoost": 0.087
    },
    {
      "ticker": "MRSH",
      "name": "Marshmello",
      "genre": "Electronic",
      "spotifyId": "64KEffDW9EtZ1y2vBYgq8T",
      "popularity": 83,
      "popularityDelta": 0,
      "followers": 34947511,
      "monthlyListeners": 53710830,
      "listenersSource": "calibrated-proxy",
      "image": "https://i.scdn.co/image/ab6761610000e5ebfa62d7b4d09a4ea9b4c5f05d",
      "fairPrice": 2.25,
      "price": 2.25,
      "chg24h": 0.0,
      "volatility30d": 0.0,
      "volume": 3547,
      "youtube": {
        "subscribers": 58500000,
        "views": 17827809128,
        "videos": 571
      },
      "youtubeViews": 17827809128,
      "youtubeSubs": 58500000,
      "youtubeBoost": 0.3,
      "chartPositions": null,
      "chartBoost": 0.0,
      "popularityBoost": 0.099
    }
  ]
}